{
  "generado": "2026-03-24 15:52",
  "fecha": "2026-03-24",
  "sueno": {
    "fecha": "2026-03-24",
    "sleep_score": null,
    "horas_dormido": 7.0,
    "deep_min": 116,
    "light_min": 203,
    "rem_min": 101,
    "awake_min": 6,
    "spo2_promedio": 95.0,
    "respiracion_promedio": 11.0,
    "estres_promedio_sueno": null
  },
  "hrv": {
    "fecha": "2026-03-24",
    "last_night_avg": 83,
    "last_night_5min_high": 123,
    "weekly_avg": 88,
    "status": "BALANCED",
    "baseline_balanced_low": 79,
    "baseline_balanced_upper": 99
  },
  "predisposicion_entrenamiento": {
    "fecha": "2026-03-24",
    "score": 75,
    "level": "HIGH",
    "feedback": "RESTED_AND_READY",
    "sleep_score": 88,
    "sleep_score_pct": 86,
    "recovery_time_hours": 19.4,
    "recovery_feedback": "MODERATE",
    "acute_load": 857,
    "acwr_pct": 91,
    "acwr_feedback": "GOOD",
    "hrv_feedback": "VERY_GOOD"
  },
  "training_status": {
    "vo2max": 55.2
  },
  "fc_reposo": 35.0,
  "body_battery": {
    "charged": 41,
    "drained": 58
  },
  "actividades_recientes": [
    {
      "activityId": 22282238548,
      "activityName": "Series",
      "startTimeLocal": "2026-03-24 06:10:34",
      "activityType": "treadmill_running",
      "distance": 10027.3701171875,
      "duration": 3555.85693359375,
      "elapsedDuration": 3555.85693359375,
      "averageSpeed": 2.8199999332427974,
      "maxSpeed": 3.200000047683716,
      "calories": 683.0,
      "averageHR": 125.0,
      "maxHR": 134.0,
      "averageRunningCadenceInStepsPerMinute": 173.84375,
      "avgStrideLength": 97.12999877929688,
      "avgVerticalOscillation": 8.230000305175782,
      "aerobicTrainingEffect": 2.9000000953674316,
      "anaerobicTrainingEffect": 0.0,
      "trainingEffectLabel": "AEROBIC_BASE",
      "activityTrainingLoad": 76.66650390625,
      "moderateIntensityMinutes": 2,
      "vigorousIntensityMinutes": 56,
      "differenceBodyBattery": -16,
      "lapCount": 41,
      "steps": 10222,
      "avgPower": 284.0,
      "maxPower": 339.0,
      "normPower": 285.0,
      "ritmo_min_km": "5:54",
      "duracion_min": 59.3,
      "distancia_km": 10.03,
      "splits": [
        {
          "km": 1,
          "distancia_m": 1000.0,
          "duracion_seg": 376.7,
          "ritmo_min_km": "6:16",
          "averageHR": 117.0,
          "maxHR": 128.0,
          "averageRunCadence": 171.65625,
          "averagePower": 268.0,
          "groundContactTime": 270.29998779296875,
          "strideLength": 92.5,
          "verticalOscillation": 8.05999984741211
        },
        {
          "km": 2,
          "distancia_m": 1000.0,
          "duracion_seg": 356.8,
          "ritmo_min_km": "5:56",
          "averageHR": 124.0,
          "maxHR": 130.0,
          "averageRunCadence": 173.859375,
          "averagePower": 284.0,
          "groundContactTime": 266.5,
          "strideLength": 96.57000122070313,
          "verticalOscillation": 8.26999969482422
        },
        {
          "km": 3,
          "distancia_m": 994.47,
          "duracion_seg": 349.8,
          "ritmo_min_km": "5:51",
          "averageHR": 125.0,
          "maxHR": 130.0,
          "averageRunCadence": 174.140625,
          "averagePower": 288.0,
          "groundContactTime": 265.1000061035156,
          "strideLength": 97.92000122070313,
          "verticalOscillation": 8.30999984741211
        },
        {
          "km": 4,
          "distancia_m": 2.66,
          "duracion_seg": 0.8,
          "ritmo_min_km": "5:06",
          "averageHR": 124.0,
          "maxHR": 124.0,
          "averageRunCadence": 170.0,
          "averagePower": 271.0,
          "groundContactTime": 275.0,
          "strideLength": 93.80000000000001,
          "verticalOscillation": 8.36999969482422
        },
        {
          "km": 5,
          "distancia_m": 2.65,
          "duracion_seg": 1.2,
          "ritmo_min_km": "7:47",
          "averageHR": 125.0,
          "maxHR": 125.0,
          "averageRunCadence": 170.0,
          "averagePower": 270.0,
          "groundContactTime": 275.0,
          "strideLength": 93.5,
          "verticalOscillation": 8.36999969482422
        },
        {
          "km": 6,
          "distancia_m": 2.65,
          "duracion_seg": 0.6,
          "ritmo_min_km": "3:55",
          "averageHR": 124.0,
          "maxHR": 124.0,
          "averageRunCadence": 170.0,
          "averagePower": 270.0,
          "groundContactTime": 275.0,
          "strideLength": 93.5,
          "verticalOscillation": 8.36999969482422
        },
        {
          "km": 7,
          "distancia_m": 2.64,
          "duracion_seg": 1.0,
          "ritmo_min_km": "6:12",
          "averageHR": 124.0,
          "maxHR": 124.0,
          "averageRunCadence": 170.0,
          "averagePower": 269.0,
          "groundContactTime": 275.0,
          "strideLength": 93.10000000000001,
          "verticalOscillation": 8.35999984741211
        },
        {
          "km": 8,
          "distancia_m": 2.64,
          "duracion_seg": 1.3,
          "ritmo_min_km": "8:00",
          "averageHR": 124.0,
          "maxHR": 124.0,
          "averageRunCadence": 170.0,
          "averagePower": 269.0,
          "groundContactTime": 275.0,
          "strideLength": 93.10000000000001,
          "verticalOscillation": 8.35999984741211
        },
        {
          "km": 9,
          "distancia_m": 2.64,
          "duracion_seg": 1.4,
          "ritmo_min_km": "8:34",
          "averageHR": 124.0,
          "maxHR": 124.0,
          "averageRunCadence": 170.0,
          "averagePower": 268.0,
          "groundContactTime": 275.0,
          "strideLength": 93.10000000000001,
          "verticalOscillation": 8.35999984741211
        },
        {
          "km": 10,
          "distancia_m": 2.61,
          "duracion_seg": 1.0,
          "ritmo_min_km": "6:25",
          "averageHR": 124.0,
          "maxHR": 124.0,
          "averageRunCadence": 170.0,
          "averagePower": 266.0,
          "groundContactTime": 276.0,
          "strideLength": 92.2,
          "verticalOscillation": 8.3
        },
        {
          "km": 11,
          "distancia_m": 2.6,
          "duracion_seg": 0.3,
          "ritmo_min_km": "1:58",
          "averageHR": 125.0,
          "maxHR": 125.0,
          "averageRunCadence": 170.0,
          "averagePower": 265.0,
          "groundContactTime": 276.0,
          "strideLength": 91.80000000000001,
          "verticalOscillation": 8.3
        },
        {
          "km": 12,
          "distancia_m": 2.62,
          "duracion_seg": 1.3,
          "ritmo_min_km": "8:28",
          "averageHR": 124.0,
          "maxHR": 124.0,
          "averageRunCadence": 170.0,
          "averagePower": 266.0,
          "groundContactTime": 276.0,
          "strideLength": 92.5,
          "verticalOscillation": 8.30999984741211
        },
        {
          "km": 13,
          "distancia_m": 2.67,
          "duracion_seg": 1.0,
          "ritmo_min_km": "6:07",
          "averageHR": 124.0,
          "maxHR": 124.0,
          "averageRunCadence": 170.0,
          "averagePower": 272.0,
          "groundContactTime": 275.0,
          "strideLength": 94.10000000000001,
          "verticalOscillation": 8.380000305175782
        },
        {
          "km": 14,
          "distancia_m": 2.68,
          "duracion_seg": 1.0,
          "ritmo_min_km": "6:19",
          "averageHR": 124.0,
          "maxHR": 124.0,
          "averageRunCadence": 170.0,
          "averagePower": 275.0,
          "groundContactTime": 274.0,
          "strideLength": 94.5,
          "verticalOscillation": 8.419999694824218
        },
        {
          "km": 15,
          "distancia_m": 8.04,
          "duracion_seg": 3.5,
          "ritmo_min_km": "7:14",
          "averageHR": 124.0,
          "maxHR": 124.0,
          "averageRunCadence": 170.0,
          "averagePower": 275.0,
          "groundContactTime": 274.0,
          "strideLength": 94.60000000000001,
          "verticalOscillation": 8.419999694824218
        },
        {
          "km": 16,
          "distancia_m": 5.31,
          "duracion_seg": 2.0,
          "ritmo_min_km": "6:07",
          "averageHR": 124.0,
          "maxHR": 124.0,
          "averageRunCadence": 175.0,
          "averagePower": 268.0,
          "groundContactTime": 271.5,
          "strideLength": 92.05000000000001,
          "verticalOscillation": 8.140000152587891
        },
        {
          "km": 17,
          "distancia_m": 5.3,
          "duracion_seg": 1.4,
          "ritmo_min_km": "4:26",
          "averageHR": 124.0,
          "maxHR": 124.0,
          "averageRunCadence": 175.0,
          "averagePower": 267.0,
          "groundContactTime": 268.0,
          "strideLength": 90.30000000000001,
          "verticalOscillation": 7.9
        },
        {
          "km": 18,
          "distancia_m": 2.69,
          "duracion_seg": 1.0,
          "ritmo_min_km": "6:10",
          "averageHR": 124.0,
          "maxHR": 124.0,
          "averageRunCadence": 175.0,
          "averagePower": 271.0,
          "groundContactTime": 267.0,
          "strideLength": 91.60000000000001,
          "verticalOscillation": 7.95999984741211
        },
        {
          "km": 19,
          "distancia_m": 2.58,
          "duracion_seg": 1.0,
          "ritmo_min_km": "6:35",
          "averageHR": 124.0,
          "maxHR": 124.0,
          "averageRunCadence": 175.0,
          "averagePower": 259.0,
          "groundContactTime": 270.0,
          "strideLength": 87.7,
          "verticalOscillation": 7.790000152587891
        },
        {
          "km": 20,
          "distancia_m": 2.5,
          "duracion_seg": 1.6,
          "ritmo_min_km": "10:40",
          "averageHR": 125.0,
          "maxHR": 125.0,
          "averageRunCadence": 175.0,
          "averagePower": 252.0,
          "groundContactTime": 272.0,
          "strideLength": 85.2,
          "verticalOscillation": 7.669999694824219
        },
        {
          "km": 21,
          "distancia_m": 2.59,
          "duracion_seg": 0.3,
          "ritmo_min_km": "2:02",
          "averageHR": 124.0,
          "maxHR": 124.0,
          "averageRunCadence": 175.0,
          "averagePower": 261.0,
          "groundContactTime": 269.0,
          "strideLength": 88.4,
          "verticalOscillation": 7.830000305175782
        },
        {
          "km": 22,
          "distancia_m": 2.64,
          "duracion_seg": 0.9,
          "ritmo_min_km": "5:40",
          "averageHR": 124.0,
          "maxHR": 124.0,
          "averageRunCadence": 175.0,
          "averagePower": 266.0,
          "groundContactTime": 268.0,
          "strideLength": 90.0,
          "verticalOscillation": 7.890000152587891
        },
        {
          "km": 23,
          "distancia_m": 2.69,
          "duracion_seg": 1.2,
          "ritmo_min_km": "7:35",
          "averageHR": 125.0,
          "maxHR": 125.0,
          "averageRunCadence": 175.0,
          "averagePower": 275.0,
          "groundContactTime": 267.0,
          "strideLength": 91.60000000000001,
          "verticalOscillation": 7.95999984741211
        },
        {
          "km": 24,
          "distancia_m": 5.47,
          "duracion_seg": 1.8,
          "ritmo_min_km": "5:22",
          "averageHR": 124.0,
          "maxHR": 124.0,
          "averageRunCadence": 175.0,
          "averagePower": 284.0,
          "groundContactTime": 266.0,
          "strideLength": 93.15,
          "verticalOscillation": 8.01999969482422
        },
        {
          "km": 25,
          "distancia_m": 2.76,
          "duracion_seg": 1.3,
          "ritmo_min_km": "8:08",
          "averageHR": 124.0,
          "maxHR": 124.0,
          "averageRunCadence": 87.0,
          "averagePower": 284.0,
          "groundContactTime": 265.0,
          "strideLength": 94.10000000000001,
          "verticalOscillation": 8.069999694824219
        },
        {
          "km": 26,
          "distancia_m": 2.74,
          "duracion_seg": 0.9,
          "ritmo_min_km": "5:35",
          "averageHR": 124.0,
          "maxHR": 124.0,
          "averageRunCadence": 87.0,
          "averagePower": 153.0,
          "strideLength": 191.3,
          "verticalOscillation": 6.95
        },
        {
          "km": 27,
          "distancia_m": 2.71,
          "duracion_seg": 1.6,
          "ritmo_min_km": "9:33",
          "averageHR": 125.0,
          "maxHR": 125.0,
          "averageRunCadence": 87.0,
          "averagePower": 147.0,
          "strideLength": 188.70000000000002,
          "verticalOscillation": 6.919999694824219
        },
        {
          "km": 28,
          "distancia_m": 2.3,
          "duracion_seg": 0.3,
          "ritmo_min_km": "2:25",
          "averageHR": 124.0,
          "maxHR": 124.0,
          "averageRunCadence": 87.0,
          "averagePower": 123.0,
          "strideLength": 160.70000000000002,
          "verticalOscillation": 6.590000152587891
        },
        {
          "km": 29,
          "distancia_m": 2.09,
          "duracion_seg": 1.6,
          "ritmo_min_km": "12:42",
          "averageHR": 124.0,
          "maxHR": 124.0,
          "averageRunCadence": 87.0,
          "averagePower": 111.0,
          "strideLength": 145.8,
          "verticalOscillation": 6.419999694824219
        },
        {
          "km": 30,
          "distancia_m": 3.78,
          "duracion_seg": 1.6,
          "ritmo_min_km": "7:08",
          "averageHR": 125.0,
          "maxHR": 125.0,
          "averageRunCadence": 87.0,
          "averagePower": 102.0,
          "strideLength": 131.8,
          "verticalOscillation": 6.25999984741211
        },
        {
          "km": 31,
          "distancia_m": 3.49,
          "duracion_seg": 1.6,
          "ritmo_min_km": "7:51",
          "averageHR": 124.0,
          "maxHR": 124.0,
          "averageRunCadence": 87.0,
          "averagePower": 95.0,
          "strideLength": 121.65,
          "verticalOscillation": 6.140000152587891
        },
        {
          "km": 32,
          "distancia_m": 1.67,
          "duracion_seg": 1.6,
          "ritmo_min_km": "16:28",
          "averageHR": 124.0,
          "maxHR": 124.0,
          "averageRunCadence": 87.0,
          "averagePower": 91.0,
          "strideLength": 116.5,
          "verticalOscillation": 6.079999923706055
        },
        {
          "km": 33,
          "distancia_m": 3.22,
          "duracion_seg": 1.3,
          "ritmo_min_km": "6:58",
          "averageHR": 123.0,
          "maxHR": 123.0,
          "averageRunCadence": 87.5,
          "averagePower": 90.0,
          "strideLength": 111.0,
          "verticalOscillation": 6.029999923706055
        },
        {
          "km": 34,
          "distancia_m": 200.0,
          "duracion_seg": 76.5,
          "ritmo_min_km": "6:22",
          "averageHR": 121.0,
          "maxHR": 123.0,
          "averageRunCadence": 165.296875,
          "averagePower": 262.0,
          "groundContactTime": 271.6000061035156,
          "strideLength": 94.99000244140626,
          "verticalOscillation": 8.130000305175782
        },
        {
          "km": 35,
          "distancia_m": 1000.0,
          "duracion_seg": 354.3,
          "ritmo_min_km": "5:54",
          "averageHR": 123.0,
          "maxHR": 126.0,
          "averageRunCadence": 174.921875,
          "averagePower": 285.0,
          "groundContactTime": 264.70001220703125,
          "strideLength": 96.60999755859376,
          "verticalOscillation": 8.200000000000001
        },
        {
          "km": 36,
          "distancia_m": 1000.0,
          "duracion_seg": 352.0,
          "ritmo_min_km": "5:52",
          "averageHR": 123.0,
          "maxHR": 126.0,
          "averageRunCadence": 174.25,
          "averagePower": 286.0,
          "groundContactTime": 265.0,
          "strideLength": 97.59000244140626,
          "verticalOscillation": 8.280000305175781
        },
        {
          "km": 37,
          "distancia_m": 1000.0,
          "duracion_seg": 349.2,
          "ritmo_min_km": "5:49",
          "averageHR": 123.0,
          "maxHR": 128.0,
          "averageRunCadence": 174.546875,
          "averagePower": 288.0,
          "groundContactTime": 264.1000061035156,
          "strideLength": 98.2,
          "verticalOscillation": 8.290000152587892
        },
        {
          "km": 38,
          "distancia_m": 1000.0,
          "duracion_seg": 348.3,
          "ritmo_min_km": "5:48",
          "averageHR": 130.0,
          "maxHR": 132.0,
          "averageRunCadence": 175.21875,
          "averagePower": 289.0,
          "groundContactTime": 263.1000061035156,
          "strideLength": 98.02999877929688,
          "verticalOscillation": 8.240000152587891
        },
        {
          "km": 39,
          "distancia_m": 1000.0,
          "duracion_seg": 345.0,
          "ritmo_min_km": "5:45",
          "averageHR": 128.0,
          "maxHR": 132.0,
          "averageRunCadence": 175.671875,
          "averagePower": 291.0,
          "groundContactTime": 262.0,
          "strideLength": 98.75,
          "verticalOscillation": 8.240000152587891
        },
        {
          "km": 40,
          "distancia_m": 1000.0,
          "duracion_seg": 349.3,
          "ritmo_min_km": "5:49",
          "averageHR": 130.0,
          "maxHR": 134.0,
          "averageRunCadence": 175.046875,
          "averagePower": 289.0,
          "groundContactTime": 263.6000061035156,
          "strideLength": 97.89000244140625,
          "verticalOscillation": 8.25
        },
        {
          "km": 41,
          "distancia_m": 739.27,
          "duracion_seg": 260.2,
          "ritmo_min_km": "5:52",
          "averageHR": 127.0,
          "maxHR": 133.0,
          "averageRunCadence": 174.390625,
          "averagePower": 286.0,
          "groundContactTime": 265.29998779296875,
          "strideLength": 97.25,
          "verticalOscillation": 8.26999969482422
        }
      ]
    },
    {
      "activityId": 22260707238,
      "activityName": "Tarifa Carrera",
      "startTimeLocal": "2026-03-22 08:15:14",
      "activityType": "running",
      "distance": 1589.469970703125,
      "duration": 655.344970703125,
      "elapsedDuration": 655.344970703125,
      "averageSpeed": 2.424999952316284,
      "maxSpeed": 2.7149999141693115,
      "calories": 128.0,
      "averageHR": 129.0,
      "maxHR": 135.0,
      "averageRunningCadenceInStepsPerMinute": 169.984375,
      "avgStrideLength": 86.17000122070313,
      "avgVerticalOscillation": 7.80999984741211,
      "elevationGain": 1.0,
      "elevationLoss": 1.0,
      "aerobicTrainingEffect": 1.600000023841858,
      "anaerobicTrainingEffect": 0.0,
      "trainingEffectLabel": "RECOVERY",
      "activityTrainingLoad": 21.352127075195312,
      "moderateIntensityMinutes": 1,
      "vigorousIntensityMinutes": 9,
      "differenceBodyBattery": -3,
      "locationName": "Tarifa",
      "lapCount": 2,
      "steps": 1842,
      "avgPower": 252.0,
      "maxPower": 314.0,
      "normPower": 256.0,
      "ritmo_min_km": "6:52",
      "duracion_min": 10.9,
      "distancia_km": 1.59,
      "splits": [
        {
          "km": 1,
          "distancia_m": 1000.0,
          "duracion_seg": 405.3,
          "ritmo_min_km": "6:45",
          "averageHR": 129.0,
          "maxHR": 135.0,
          "averageRunCadence": 170.703125,
          "averagePower": 255.0,
          "groundContactTime": 276.29998779296875,
          "strideLength": 86.60000000000001,
          "verticalOscillation": 7.830000305175782,
          "elevationGain": 1.0,
          "elevationLoss": 1.0
        },
        {
          "km": 2,
          "distancia_m": 589.47,
          "duracion_seg": 250.1,
          "ritmo_min_km": "7:04",
          "averageHR": 128.0,
          "maxHR": 132.0,
          "averageRunCadence": 168.8125,
          "averagePower": 247.0,
          "groundContactTime": 284.5,
          "strideLength": 85.47999877929688,
          "verticalOscillation": 7.800000000000001,
          "elevationGain": 0.0,
          "elevationLoss": 0.0
        }
      ]
    },
    {
      "activityId": 22260705875,
      "activityName": "Tarifa - Continuo suave",
      "startTimeLocal": "2026-03-22 06:24:56",
      "activityType": "running",
      "distance": 18359.169921875,
      "duration": 5931.26904296875,
      "elapsedDuration": 5931.26904296875,
      "averageSpeed": 3.0950000286102295,
      "maxSpeed": 4.14300012588501,
      "calories": 1347.0,
      "averageHR": 138.0,
      "maxHR": 166.0,
      "averageRunningCadenceInStepsPerMinute": 176.03125,
      "avgStrideLength": 104.6199951171875,
      "avgVerticalOscillation": 8.290000152587892,
      "elevationGain": 7.0,
      "elevationLoss": 6.0,
      "aerobicTrainingEffect": 4.800000190734863,
      "anaerobicTrainingEffect": 2.0999999046325684,
      "trainingEffectLabel": "VO2MAX",
      "activityTrainingLoad": 303.9169921875,
      "moderateIntensityMinutes": 1,
      "vigorousIntensityMinutes": 97,
      "differenceBodyBattery": -28,
      "locationName": "Tarifa",
      "lapCount": 19,
      "steps": 17414,
      "avgPower": 316.0,
      "maxPower": 456.0,
      "normPower": 327.0,
      "ritmo_min_km": "5:23",
      "duracion_min": 98.9,
      "distancia_km": 18.36,
      "splits": [
        {
          "km": 1,
          "distancia_m": 1000.0,
          "duracion_seg": 356.9,
          "ritmo_min_km": "5:56",
          "averageHR": 110.0,
          "maxHR": 120.0,
          "averageRunCadence": 174.5,
          "averagePower": 283.0,
          "groundContactTime": 262.20001220703125,
          "strideLength": 94.49000244140626,
          "verticalOscillation": 7.95,
          "elevationGain": 0.0,
          "elevationLoss": 0.0
        },
        {
          "km": 2,
          "distancia_m": 1000.0,
          "duracion_seg": 344.6,
          "ritmo_min_km": "5:44",
          "averageHR": 127.0,
          "maxHR": 133.0,
          "averageRunCadence": 178.75,
          "averagePower": 297.0,
          "groundContactTime": 258.29998779296875,
          "strideLength": 97.42999877929688,
          "verticalOscillation": 8.0,
          "elevationGain": 2.0,
          "elevationLoss": 2.0
        },
        {
          "km": 3,
          "distancia_m": 1000.0,
          "duracion_seg": 347.0,
          "ritmo_min_km": "5:47",
          "averageHR": 126.0,
          "maxHR": 132.0,
          "averageRunCadence": 177.09375,
          "averagePower": 293.0,
          "groundContactTime": 261.0,
          "strideLength": 97.14000244140625,
          "verticalOscillation": 8.1,
          "elevationGain": 2.0,
          "elevationLoss": 0.0
        },
        {
          "km": 4,
          "distancia_m": 1000.0,
          "duracion_seg": 348.0,
          "ritmo_min_km": "5:47",
          "averageHR": 128.0,
          "maxHR": 134.0,
          "averageRunCadence": 177.296875,
          "averagePower": 291.0,
          "groundContactTime": 260.6000061035156,
          "strideLength": 96.97999877929688,
          "verticalOscillation": 8.069999694824219,
          "elevationGain": 0.0,
          "elevationLoss": 0.0
        },
        {
          "km": 5,
          "distancia_m": 1000.0,
          "duracion_seg": 337.1,
          "ritmo_min_km": "5:37",
          "averageHR": 132.0,
          "maxHR": 135.0,
          "averageRunCadence": 176.78125,
          "averagePower": 301.0,
          "groundContactTime": 259.0,
          "strideLength": 100.42999877929688,
          "verticalOscillation": 8.240000152587891,
          "elevationGain": 0.0,
          "elevationLoss": 1.0
        },
        {
          "km": 6,
          "distancia_m": 1000.0,
          "duracion_seg": 334.3,
          "ritmo_min_km": "5:34",
          "averageHR": 137.0,
          "maxHR": 139.0,
          "averageRunCadence": 177.125,
          "averagePower": 306.0,
          "groundContactTime": 257.70001220703125,
          "strideLength": 101.40999755859376,
          "verticalOscillation": 8.25,
          "elevationGain": 0.0,
          "elevationLoss": 0.0
        },
        {
          "km": 7,
          "distancia_m": 1000.0,
          "duracion_seg": 347.6,
          "ritmo_min_km": "5:47",
          "averageHR": 132.0,
          "maxHR": 138.0,
          "averageRunCadence": 176.390625,
          "averagePower": 296.0,
          "groundContactTime": 262.1000061035156,
          "strideLength": 96.99000244140626,
          "verticalOscillation": 8.130000305175782,
          "elevationGain": 0.0,
          "elevationLoss": 0.0
        },
        {
          "km": 8,
          "distancia_m": 1000.0,
          "duracion_seg": 343.1,
          "ritmo_min_km": "5:43",
          "averageHR": 133.0,
          "maxHR": 139.0,
          "averageRunCadence": 176.953125,
          "averagePower": 303.0,
          "groundContactTime": 259.6000061035156,
          "strideLength": 99.0,
          "verticalOscillation": 8.169999694824218,
          "elevationGain": 0.0,
          "elevationLoss": 1.0
        },
        {
          "km": 9,
          "distancia_m": 1000.0,
          "duracion_seg": 347.0,
          "ritmo_min_km": "5:47",
          "averageHR": 136.0,
          "maxHR": 140.0,
          "averageRunCadence": 175.21875,
          "averagePower": 297.0,
          "groundContactTime": 263.1000061035156,
          "strideLength": 98.12000122070313,
          "verticalOscillation": 8.25,
          "elevationGain": 0.0,
          "elevationLoss": 0.0
        },
        {
          "km": 10,
          "distancia_m": 1000.0,
          "duracion_seg": 352.8,
          "ritmo_min_km": "5:52",
          "averageHR": 134.0,
          "maxHR": 140.0,
          "averageRunCadence": 174.65625,
          "averagePower": 290.0,
          "groundContactTime": 264.79998779296875,
          "strideLength": 97.02000122070314,
          "verticalOscillation": 8.230000305175782,
          "elevationGain": 0.0,
          "elevationLoss": 1.0
        },
        {
          "km": 11,
          "distancia_m": 1000.0,
          "duracion_seg": 334.5,
          "ritmo_min_km": "5:34",
          "averageHR": 136.0,
          "maxHR": 142.0,
          "averageRunCadence": 177.53125,
          "averagePower": 303.0,
          "groundContactTime": 257.79998779296875,
          "strideLength": 100.40999755859376,
          "verticalOscillation": 8.19000015258789,
          "elevationGain": 0.0,
          "elevationLoss": 0.0
        },
        {
          "km": 12,
          "distancia_m": 1000.0,
          "duracion_seg": 330.8,
          "ritmo_min_km": "5:30",
          "averageHR": 137.0,
          "maxHR": 142.0,
          "averageRunCadence": 176.84375,
          "averagePower": 306.0,
          "groundContactTime": 257.70001220703125,
          "strideLength": 102.22999877929688,
          "verticalOscillation": 8.30999984741211,
          "elevationGain": 0.0,
          "elevationLoss": 0.0
        },
        {
          "km": 13,
          "distancia_m": 1000.0,
          "duracion_seg": 317.1,
          "ritmo_min_km": "5:17",
          "averageHR": 143.0,
          "maxHR": 152.0,
          "averageRunCadence": 172.140625,
          "averagePower": 312.0,
          "groundContactTime": 254.39999389648438,
          "strideLength": 106.0199951171875,
          "verticalOscillation": 8.430000305175781,
          "elevationGain": 1.0,
          "elevationLoss": 0.0
        },
        {
          "km": 14,
          "distancia_m": 1000.0,
          "duracion_seg": 266.6,
          "ritmo_min_km": "4:26",
          "averageHR": 160.0,
          "maxHR": 166.0,
          "averageRunCadence": 183.53125,
          "averagePower": 386.0,
          "groundContactTime": 233.1999969482422,
          "strideLength": 121.35999755859376,
          "verticalOscillation": 8.540000152587892,
          "elevationGain": 1.0,
          "elevationLoss": 0.0
        },
        {
          "km": 15,
          "distancia_m": 1000.0,
          "duracion_seg": 263.9,
          "ritmo_min_km": "4:23",
          "averageHR": 159.0,
          "maxHR": 161.0,
          "averageRunCadence": 182.375,
          "averagePower": 391.0,
          "groundContactTime": 232.5,
          "strideLength": 124.23000488281251,
          "verticalOscillation": 8.69000015258789,
          "elevationGain": 0.0,
          "elevationLoss": 0.0
        },
        {
          "km": 16,
          "distancia_m": 1000.0,
          "duracion_seg": 260.9,
          "ritmo_min_km": "4:20",
          "averageHR": 159.0,
          "maxHR": 163.0,
          "averageRunCadence": 179.890625,
          "averagePower": 392.0,
          "groundContactTime": 234.1999969482422,
          "strideLength": 126.65,
          "verticalOscillation": 8.930000305175781,
          "elevationGain": 0.0,
          "elevationLoss": 1.0
        },
        {
          "km": 17,
          "distancia_m": 1000.0,
          "duracion_seg": 257.2,
          "ritmo_min_km": "4:17",
          "averageHR": 155.0,
          "maxHR": 163.0,
          "averageRunCadence": 179.1875,
          "averagePower": 400.0,
          "groundContactTime": 232.89999389648438,
          "strideLength": 129.7300048828125,
          "verticalOscillation": 9.080000305175782,
          "elevationGain": 0.0,
          "elevationLoss": 0.0
        },
        {
          "km": 18,
          "distancia_m": 1000.0,
          "duracion_seg": 253.3,
          "ritmo_min_km": "4:13",
          "averageHR": 161.0,
          "maxHR": 166.0,
          "averageRunCadence": 180.09375,
          "averagePower": 407.0,
          "groundContactTime": 229.89999389648438,
          "strideLength": 131.65999755859374,
          "verticalOscillation": 9.069999694824219,
          "elevationGain": 1.0,
          "elevationLoss": 0.0
        },
        {
          "km": 19,
          "distancia_m": 359.17,
          "duracion_seg": 188.4,
          "ritmo_min_km": "8:44",
          "averageHR": 141.0,
          "maxHR": 160.0,
          "averageRunCadence": 135.65625,
          "averagePower": 180.0,
          "groundContactTime": 278.8999938964844,
          "strideLength": 84.10999755859376,
          "verticalOscillation": 6.95999984741211,
          "elevationGain": 0.0,
          "elevationLoss": 0.0
        }
      ]
    },
    {
      "activityId": 22251154153,
      "activityName": "Colonche Natación en aguas abiertas",
      "startTimeLocal": "2026-03-21 11:19:05",
      "activityType": "open_water_swimming",
      "distance": 228.97999572753906,
      "duration": 316.5780029296875,
      "elapsedDuration": 389.6570129394531,
      "averageSpeed": 0.7229999899864196,
      "maxSpeed": 1.4479999542236328,
      "calories": 51.0,
      "averageHR": 104.0,
      "maxHR": 128.0,
      "aerobicTrainingEffect": 0.6000000238418579,
      "anaerobicTrainingEffect": 0.4000000059604645,
      "trainingEffectLabel": "RECOVERY",
      "activityTrainingLoad": 15.168746948242188,
      "moderateIntensityMinutes": 0,
      "vigorousIntensityMinutes": 3,
      "differenceBodyBattery": -1,
      "locationName": "Colonche",
      "lapCount": 2,
      "ritmo_min_km": "23:03",
      "duracion_min": 5.3,
      "distancia_km": 0.23
    },
    {
      "activityId": 22225665822,
      "activityName": "Tarifa Carrera",
      "startTimeLocal": "2026-03-19 05:44:59",
      "activityType": "running",
      "distance": 16682.419921875,
      "duration": 5494.205078125,
      "elapsedDuration": 5585.51708984375,
      "averageSpeed": 3.036000013351441,
      "maxSpeed": 4.63700008392334,
      "calories": 1227.0,
      "averageHR": 138.0,
      "maxHR": 166.0,
      "averageRunningCadenceInStepsPerMinute": 173.578125,
      "avgStrideLength": 103.68000488281251,
      "avgVerticalOscillation": 8.009999847412109,
      "elevationGain": 6.0,
      "elevationLoss": 10.0,
      "aerobicTrainingEffect": 4.5,
      "anaerobicTrainingEffect": 3.0,
      "trainingEffectLabel": "VO2MAX",
      "activityTrainingLoad": 319.18084716796875,
      "moderateIntensityMinutes": 4,
      "vigorousIntensityMinutes": 87,
      "differenceBodyBattery": -28,
      "locationName": "Tarifa",
      "lapCount": 27,
      "steps": 16002,
      "avgPower": 309.0,
      "maxPower": 471.0,
      "normPower": 336.0,
      "ritmo_min_km": "5:29",
      "duracion_min": 91.6,
      "distancia_km": 16.68,
      "splits": [
        {
          "km": 1,
          "distancia_m": 1000.0,
          "duracion_seg": 349.8,
          "ritmo_min_km": "5:49",
          "averageHR": 119.0,
          "maxHR": 127.0,
          "averageRunCadence": 175.078125,
          "averagePower": 290.0,
          "groundContactTime": 259.5,
          "strideLength": 96.64000244140625,
          "verticalOscillation": 7.990000152587891,
          "elevationGain": 0.0,
          "elevationLoss": 1.0
        },
        {
          "km": 2,
          "distancia_m": 1000.0,
          "duracion_seg": 354.1,
          "ritmo_min_km": "5:54",
          "averageHR": 126.0,
          "maxHR": 133.0,
          "averageRunCadence": 177.4375,
          "averagePower": 293.0,
          "groundContactTime": 261.70001220703125,
          "strideLength": 95.15999755859376,
          "verticalOscillation": 7.990000152587891,
          "elevationGain": 1.0,
          "elevationLoss": 1.0
        },
        {
          "km": 3,
          "distancia_m": 1000.0,
          "duracion_seg": 382.0,
          "ritmo_min_km": "6:21",
          "averageHR": 117.0,
          "maxHR": 126.0,
          "averageRunCadence": 167.515625,
          "averagePower": 267.0,
          "groundContactTime": 268.20001220703125,
          "strideLength": 93.25999755859375,
          "verticalOscillation": 8.069999694824219,
          "elevationGain": 0.0,
          "elevationLoss": 0.0
        },
        {
          "km": 4,
          "distancia_m": 1000.0,
          "duracion_seg": 376.3,
          "ritmo_min_km": "6:16",
          "averageHR": 118.0,
          "maxHR": 121.0,
          "averageRunCadence": 175.921875,
          "averagePower": 274.0,
          "groundContactTime": 267.1000061035156,
          "strideLength": 91.05000000000001,
          "verticalOscillation": 7.909999847412109,
          "elevationGain": 0.0,
          "elevationLoss": 0.0
        },
        {
          "km": 5,
          "distancia_m": 79.01,
          "duracion_seg": 30.4,
          "ritmo_min_km": "6:24",
          "averageHR": 115.0,
          "maxHR": 116.0,
          "averageRunCadence": 176.859375,
          "averagePower": 269.0,
          "groundContactTime": 267.79998779296875,
          "strideLength": 87.77000122070314,
          "verticalOscillation": 7.719999694824219,
          "elevationGain": 0.0,
          "elevationLoss": 0.0
        },
        {
          "km": 6,
          "distancia_m": 809.0,
          "duracion_seg": 215.3,
          "ritmo_min_km": "4:26",
          "averageHR": 141.0,
          "maxHR": 151.0,
          "averageRunCadence": 186.375,
          "averagePower": 375.0,
          "groundContactTime": 231.5,
          "strideLength": 118.30000000000001,
          "verticalOscillation": 8.259999847412109,
          "elevationGain": 0.0,
          "elevationLoss": 0.0
        },
        {
          "km": 7,
          "distancia_m": 186.1,
          "duracion_seg": 77.8,
          "ritmo_min_km": "6:58",
          "averageHR": 140.0,
          "maxHR": 151.0,
          "averageRunCadence": 172.8125,
          "averagePower": 277.0,
          "groundContactTime": 271.1000061035156,
          "strideLength": 94.24000244140626,
          "verticalOscillation": 8.140000152587891,
          "elevationGain": 0.0,
          "elevationLoss": 0.0
        },
        {
          "km": 8,
          "distancia_m": 810.73,
          "duracion_seg": 215.5,
          "ritmo_min_km": "4:25",
          "averageHR": 153.0,
          "maxHR": 159.0,
          "averageRunCadence": 186.171875,
          "averagePower": 382.0,
          "groundContactTime": 230.1999969482422,
          "strideLength": 120.24000244140626,
          "verticalOscillation": 8.319999694824219,
          "elevationGain": 0.0,
          "elevationLoss": 0.0
        },
        {
          "km": 9,
          "distancia_m": 201.83,
          "duracion_seg": 84.1,
          "ritmo_min_km": "6:56",
          "averageHR": 142.0,
          "maxHR": 155.0,
          "averageRunCadence": 173.46875,
          "averagePower": 271.0,
          "groundContactTime": 271.5,
          "strideLength": 90.99000244140626,
          "verticalOscillation": 8.040000152587892,
          "elevationGain": 0.0,
          "elevationLoss": 1.0
        },
        {
          "km": 10,
          "distancia_m": 818.78,
          "duracion_seg": 215.4,
          "ritmo_min_km": "4:23",
          "averageHR": 146.0,
          "maxHR": 154.0,
          "averageRunCadence": 185.796875,
          "averagePower": 383.0,
          "groundContactTime": 230.10000610351562,
          "strideLength": 120.85999755859376,
          "verticalOscillation": 8.35999984741211,
          "elevationGain": 0.0,
          "elevationLoss": 0.0
        },
        {
          "km": 11,
          "distancia_m": 236.33,
          "duracion_seg": 96.3,
          "ritmo_min_km": "6:47",
          "averageHR": 138.0,
          "maxHR": 152.0,
          "averageRunCadence": 173.90625,
          "averagePower": 274.0,
          "groundContactTime": 270.6000061035156,
          "strideLength": 91.22000122070312,
          "verticalOscillation": 8.030000305175781,
          "elevationGain": 0.0,
          "elevationLoss": 0.0
        },
        {
          "km": 12,
          "distancia_m": 799.89,
          "duracion_seg": 206.7,
          "ritmo_min_km": "4:18",
          "averageHR": 149.0,
          "maxHR": 156.0,
          "averageRunCadence": 186.6875,
          "averagePower": 385.0,
          "groundContactTime": 228.3000030517578,
          "strideLength": 121.60000000000001,
          "verticalOscillation": 8.330000305175782,
          "elevationGain": 0.0,
          "elevationLoss": 0.0
        },
        {
          "km": 13,
          "distancia_m": 229.4,
          "duracion_seg": 98.6,
          "ritmo_min_km": "7:09",
          "averageHR": 142.0,
          "maxHR": 155.0,
          "averageRunCadence": 169.5,
          "averagePower": 267.0,
          "groundContactTime": 274.3999938964844,
          "strideLength": 91.57999877929689,
          "verticalOscillation": 8.01999969482422,
          "elevationGain": 0.0,
          "elevationLoss": 0.0
        },
        {
          "km": 14,
          "distancia_m": 795.28,
          "duracion_seg": 201.2,
          "ritmo_min_km": "4:13",
          "averageHR": 153.0,
          "maxHR": 159.0,
          "averageRunCadence": 187.203125,
          "averagePower": 397.0,
          "groundContactTime": 225.6999969482422,
          "strideLength": 124.00999755859375,
          "verticalOscillation": 8.36999969482422,
          "elevationGain": 0.0,
          "elevationLoss": 0.0
        },
        {
          "km": 15,
          "distancia_m": 249.68,
          "duracion_seg": 109.8,
          "ritmo_min_km": "7:19",
          "averageHR": 143.0,
          "maxHR": 159.0,
          "averageRunCadence": 171.59375,
          "averagePower": 261.0,
          "groundContactTime": 274.0,
          "strideLength": 88.17000122070313,
          "verticalOscillation": 7.940000152587891,
          "elevationGain": 0.0,
          "elevationLoss": 0.0
        },
        {
          "km": 16,
          "distancia_m": 803.61,
          "duracion_seg": 199.3,
          "ritmo_min_km": "4:07",
          "averageHR": 150.0,
          "maxHR": 158.0,
          "averageRunCadence": 186.125,
          "averagePower": 396.0,
          "groundContactTime": 225.5,
          "strideLength": 124.54000244140626,
          "verticalOscillation": 8.390000152587891,
          "elevationGain": 1.0,
          "elevationLoss": 0.0
        },
        {
          "km": 17,
          "distancia_m": 280.79,
          "duracion_seg": 127.7,
          "ritmo_min_km": "7:34",
          "averageHR": 138.0,
          "maxHR": 159.0,
          "averageRunCadence": 168.609375,
          "averagePower": 239.0,
          "groundContactTime": 280.70001220703125,
          "strideLength": 81.92000122070313,
          "verticalOscillation": 7.590000152587891,
          "elevationGain": 0.0,
          "elevationLoss": 0.0
        },
        {
          "km": 18,
          "distancia_m": 794.96,
          "duracion_seg": 201.4,
          "ritmo_min_km": "4:13",
          "averageHR": 152.0,
          "maxHR": 159.0,
          "averageRunCadence": 186.0625,
          "averagePower": 401.0,
          "groundContactTime": 226.0,
          "strideLength": 125.39000244140625,
          "verticalOscillation": 8.469999694824219,
          "elevationGain": 0.0,
          "elevationLoss": 0.0
        },
        {
          "km": 19,
          "distancia_m": 242.28,
          "duracion_seg": 142.2,
          "ritmo_min_km": "9:46",
          "averageHR": 136.0,
          "maxHR": 160.0,
          "averageRunCadence": 119.171875,
          "averagePower": 166.0,
          "groundContactTime": 277.79998779296875,
          "strideLength": 87.30000000000001,
          "verticalOscillation": 7.240000152587891,
          "elevationGain": 0.0,
          "elevationLoss": 0.0
        },
        {
          "km": 20,
          "distancia_m": 819.56,
          "duracion_seg": 205.6,
          "ritmo_min_km": "4:10",
          "averageHR": 153.0,
          "maxHR": 162.0,
          "averageRunCadence": 187.25,
          "averagePower": 404.0,
          "groundContactTime": 223.6999969482422,
          "strideLength": 126.3800048828125,
          "verticalOscillation": 8.44000015258789,
          "elevationGain": 0.0,
          "elevationLoss": 0.0
        },
        {
          "km": 21,
          "distancia_m": 292.25,
          "duracion_seg": 154.3,
          "ritmo_min_km": "8:47",
          "averageHR": 135.0,
          "maxHR": 160.0,
          "averageRunCadence": 134.265625,
          "averagePower": 176.0,
          "groundContactTime": 280.8999938964844,
          "strideLength": 80.30999755859375,
          "verticalOscillation": 7.090000152587891,
          "elevationGain": 1.0,
          "elevationLoss": 1.0
        },
        {
          "km": 22,
          "distancia_m": 828.12,
          "duracion_seg": 201.8,
          "ritmo_min_km": "4:03",
          "averageHR": 153.0,
          "maxHR": 163.0,
          "averageRunCadence": 187.296875,
          "averagePower": 422.0,
          "groundContactTime": 220.0,
          "strideLength": 130.59000244140626,
          "verticalOscillation": 8.55,
          "elevationGain": 1.0,
          "elevationLoss": 1.0
        },
        {
          "km": 23,
          "distancia_m": 206.03,
          "duracion_seg": 146.8,
          "ritmo_min_km": "11:52",
          "averageHR": 134.0,
          "maxHR": 163.0,
          "averageRunCadence": 86.65625,
          "averagePower": 95.0,
          "groundContactTime": 256.29998779296875,
          "strideLength": 77.12000122070313,
          "verticalOscillation": 6.1099998474121096,
          "elevationGain": 0.0,
          "elevationLoss": 1.0
        },
        {
          "km": 24,
          "distancia_m": 903.96,
          "duracion_seg": 209.0,
          "ritmo_min_km": "3:51",
          "averageHR": 159.0,
          "maxHR": 166.0,
          "averageRunCadence": 188.15625,
          "averagePower": 438.0,
          "groundContactTime": 213.0,
          "strideLength": 137.2699951171875,
          "verticalOscillation": 8.69000015258789,
          "elevationGain": 0.0,
          "elevationLoss": 0.0
        },
        {
          "km": 25,
          "distancia_m": 1000.0,
          "duracion_seg": 387.5,
          "ritmo_min_km": "6:27",
          "averageHR": 141.0,
          "maxHR": 165.0,
          "averageRunCadence": 167.46875,
          "averagePower": 261.0,
          "groundContactTime": 267.3999938964844,
          "strideLength": 91.60999755859376,
          "verticalOscillation": 7.780000305175782,
          "elevationGain": 0.0,
          "elevationLoss": 1.0
        },
        {
          "km": 26,
          "distancia_m": 1000.0,
          "duracion_seg": 392.4,
          "ritmo_min_km": "6:32",
          "averageHR": 137.0,
          "maxHR": 142.0,
          "averageRunCadence": 178.625,
          "averagePower": 262.0,
          "groundContactTime": 266.79998779296875,
          "strideLength": 85.70999755859376,
          "verticalOscillation": 7.550000000000001,
          "elevationGain": 1.0,
          "elevationLoss": 1.0
        },
        {
          "km": 27,
          "distancia_m": 294.83,
          "duracion_seg": 112.9,
          "ritmo_min_km": "6:22",
          "averageHR": 135.0,
          "maxHR": 138.0,
          "averageRunCadence": 178.5,
          "averagePower": 255.0,
          "groundContactTime": 266.8999938964844,
          "strideLength": 85.54000244140626,
          "verticalOscillation": 7.540000152587891,
          "elevationGain": 0.0,
          "elevationLoss": 1.0
        }
      ]
    },
    {
      "activityId": 22214451759,
      "activityName": "Tarifa - Continuo suave",
      "startTimeLocal": "2026-03-18 07:06:05",
      "activityType": "running",
      "distance": 10240.9501953125,
      "duration": 3798.69189453125,
      "elapsedDuration": 3798.69189453125,
      "averageSpeed": 2.696000099182129,
      "maxSpeed": 3.246999979019165,
      "calories": 776.0,
      "averageHR": 127.0,
      "maxHR": 138.0,
      "averageRunningCadenceInStepsPerMinute": 174.1875,
      "avgStrideLength": 92.60999755859376,
      "avgVerticalOscillation": 7.990000152587891,
      "elevationGain": 9.0,
      "elevationLoss": 9.0,
      "aerobicTrainingEffect": 3.200000047683716,
      "anaerobicTrainingEffect": 0.0,
      "trainingEffectLabel": "AEROBIC_BASE",
      "activityTrainingLoad": 100.46084594726562,
      "moderateIntensityMinutes": 1,
      "vigorousIntensityMinutes": 61,
      "differenceBodyBattery": -17,
      "locationName": "Tarifa",
      "lapCount": 11,
      "steps": 11014,
      "avgPower": 276.0,
      "maxPower": 361.0,
      "normPower": 279.0,
      "ritmo_min_km": "6:10",
      "duracion_min": 63.3,
      "distancia_km": 10.24,
      "splits": [
        {
          "km": 1,
          "distancia_m": 1000.0,
          "duracion_seg": 424.2,
          "ritmo_min_km": "7:04",
          "averageHR": 104.0,
          "maxHR": 117.0,
          "averageRunCadence": 170.84375,
          "averagePower": 243.0,
          "groundContactTime": 279.70001220703125,
          "strideLength": 82.50999755859375,
          "verticalOscillation": 7.730000305175782,
          "elevationGain": 1.0,
          "elevationLoss": 1.0
        },
        {
          "km": 2,
          "distancia_m": 1000.0,
          "duracion_seg": 366.1,
          "ritmo_min_km": "6:06",
          "averageHR": 122.0,
          "maxHR": 128.0,
          "averageRunCadence": 175.65625,
          "averagePower": 281.0,
          "groundContactTime": 265.70001220703125,
          "strideLength": 93.49000244140626,
          "verticalOscillation": 8.030000305175781,
          "elevationGain": 3.0,
          "elevationLoss": 2.0
        },
        {
          "km": 3,
          "distancia_m": 1000.0,
          "duracion_seg": 376.4,
          "ritmo_min_km": "6:16",
          "averageHR": 123.0,
          "maxHR": 129.0,
          "averageRunCadence": 169.671875,
          "averagePower": 270.0,
          "groundContactTime": 265.70001220703125,
          "strideLength": 93.32000122070313,
          "verticalOscillation": 7.930000305175781,
          "elevationGain": 1.0,
          "elevationLoss": 0.0
        },
        {
          "km": 4,
          "distancia_m": 1000.0,
          "duracion_seg": 354.8,
          "ritmo_min_km": "5:54",
          "averageHR": 129.0,
          "maxHR": 136.0,
          "averageRunCadence": 175.5625,
          "averagePower": 287.0,
          "groundContactTime": 264.20001220703125,
          "strideLength": 95.9,
          "verticalOscillation": 8.140000152587891,
          "elevationGain": 1.0,
          "elevationLoss": 1.0
        },
        {
          "km": 5,
          "distancia_m": 1000.0,
          "duracion_seg": 348.4,
          "ritmo_min_km": "5:48",
          "averageHR": 134.0,
          "maxHR": 137.0,
          "averageRunCadence": 176.09375,
          "averagePower": 293.0,
          "groundContactTime": 261.8999938964844,
          "strideLength": 97.85999755859376,
          "verticalOscillation": 8.180000305175781,
          "elevationGain": 0.0,
          "elevationLoss": 1.0
        },
        {
          "km": 6,
          "distancia_m": 1000.0,
          "duracion_seg": 354.6,
          "ritmo_min_km": "5:54",
          "averageHR": 133.0,
          "maxHR": 137.0,
          "averageRunCadence": 176.046875,
          "averagePower": 287.0,
          "groundContactTime": 263.79998779296875,
          "strideLength": 95.37000122070313,
          "verticalOscillation": 8.09000015258789,
          "elevationGain": 0.0,
          "elevationLoss": 1.0
        },
        {
          "km": 7,
          "distancia_m": 1000.0,
          "duracion_seg": 359.4,
          "ritmo_min_km": "5:59",
          "averageHR": 133.0,
          "maxHR": 137.0,
          "averageRunCadence": 175.984375,
          "averagePower": 285.0,
          "groundContactTime": 264.29998779296875,
          "strideLength": 94.55000000000001,
          "verticalOscillation": 8.05,
          "elevationGain": 0.0,
          "elevationLoss": 0.0
        },
        {
          "km": 8,
          "distancia_m": 1000.0,
          "duracion_seg": 366.1,
          "ritmo_min_km": "6:06",
          "averageHR": 133.0,
          "maxHR": 137.0,
          "averageRunCadence": 175.046875,
          "averagePower": 279.0,
          "groundContactTime": 264.70001220703125,
          "strideLength": 93.12999877929688,
          "verticalOscillation": 7.95999984741211,
          "elevationGain": 0.0,
          "elevationLoss": 0.0
        },
        {
          "km": 9,
          "distancia_m": 1000.0,
          "duracion_seg": 367.1,
          "ritmo_min_km": "6:07",
          "averageHR": 133.0,
          "maxHR": 137.0,
          "averageRunCadence": 175.625,
          "averagePower": 280.0,
          "groundContactTime": 266.3999938964844,
          "strideLength": 92.62000122070313,
          "verticalOscillation": 7.990000152587891,
          "elevationGain": 1.0,
          "elevationLoss": 2.0
        },
        {
          "km": 10,
          "distancia_m": 1000.0,
          "duracion_seg": 384.8,
          "ritmo_min_km": "6:24",
          "averageHR": 131.0,
          "maxHR": 138.0,
          "averageRunCadence": 172.640625,
          "averagePower": 266.0,
          "groundContactTime": 269.0,
          "strideLength": 90.14000244140625,
          "verticalOscillation": 7.830000305175782,
          "elevationGain": 0.0,
          "elevationLoss": 0.0
        },
        {
          "km": 11,
          "distancia_m": 240.95,
          "duracion_seg": 96.9,
          "ritmo_min_km": "6:42",
          "averageHR": 129.0,
          "maxHR": 133.0,
          "averageRunCadence": 173.046875,
          "averagePower": 273.0,
          "groundContactTime": 272.20001220703125,
          "strideLength": 90.12999877929688,
          "verticalOscillation": 8.030000305175781,
          "elevationGain": 1.0,
          "elevationLoss": 0.0
        }
      ]
    },
    {
      "activityId": 22201874191,
      "activityName": "Tarifa - Series",
      "startTimeLocal": "2026-03-17 05:27:41",
      "activityType": "running",
      "distance": 12179.51953125,
      "duration": 4302.8759765625,
      "elapsedDuration": 4534.2470703125,
      "averageSpeed": 2.8310000896453857,
      "maxSpeed": 5.813000202178955,
      "calories": 932.0,
      "averageHR": 135.0,
      "maxHR": 165.0,
      "averageRunningCadenceInStepsPerMinute": 165.953125,
      "avgStrideLength": 100.15,
      "avgVerticalOscillation": 7.740000152587891,
      "elevationGain": 14.0,
      "elevationLoss": 20.0,
      "aerobicTrainingEffect": 4.099999904632568,
      "anaerobicTrainingEffect": 3.4000000953674316,
      "trainingEffectLabel": "TEMPO",
      "activityTrainingLoad": 311.196044921875,
      "moderateIntensityMinutes": 4,
      "vigorousIntensityMinutes": 70,
      "differenceBodyBattery": -23,
      "locationName": "Tarifa",
      "lapCount": 35,
      "steps": 12038,
      "avgPower": 283.0,
      "maxPower": 578.0,
      "normPower": 332.0,
      "ritmo_min_km": "5:53",
      "duracion_min": 71.7,
      "distancia_km": 12.18,
      "splits": [
        {
          "km": 1,
          "distancia_m": 1000.0,
          "duracion_seg": 371.8,
          "ritmo_min_km": "6:11",
          "averageHR": 113.0,
          "maxHR": 122.0,
          "averageRunCadence": 180.453125,
          "averagePower": 275.0,
          "groundContactTime": 262.1000061035156,
          "strideLength": 88.80999755859375,
          "verticalOscillation": 7.569999694824219,
          "elevationGain": 0.0,
          "elevationLoss": 0.0
        },
        {
          "km": 2,
          "distancia_m": 1000.0,
          "duracion_seg": 366.3,
          "ritmo_min_km": "6:06",
          "averageHR": 120.0,
          "maxHR": 129.0,
          "averageRunCadence": 178.59375,
          "averagePower": 286.0,
          "groundContactTime": 262.6000061035156,
          "strideLength": 91.80000000000001,
          "verticalOscillation": 7.800000000000001,
          "elevationGain": 4.0,
          "elevationLoss": 3.0
        },
        {
          "km": 3,
          "distancia_m": 692.25,
          "duracion_seg": 250.3,
          "ritmo_min_km": "6:01",
          "averageHR": 122.0,
          "maxHR": 125.0,
          "averageRunCadence": 176.59375,
          "averagePower": 286.0,
          "groundContactTime": 263.79998779296875,
          "strideLength": 94.07999877929689,
          "verticalOscillation": 8.0,
          "elevationGain": 0.0,
          "elevationLoss": 0.0
        },
        {
          "km": 4,
          "distancia_m": 16.73,
          "duracion_seg": 11.5,
          "ritmo_min_km": "11:26",
          "averageHR": 121.0,
          "maxHR": 122.0,
          "averageRunCadence": 162.421875,
          "averagePower": 242.0,
          "groundContactTime": 274.29998779296875,
          "strideLength": 90.32999877929689,
          "verticalOscillation": 7.719999694824219,
          "elevationGain": 0.0,
          "elevationLoss": 0.0
        },
        {
          "km": 5,
          "distancia_m": 43.13,
          "duracion_seg": 20.5,
          "ritmo_min_km": "7:56",
          "averageHR": 118.0,
          "maxHR": 120.0,
          "averageRunCadence": 135.25,
          "averagePower": 211.0,
          "groundContactTime": 284.1000061035156,
          "strideLength": 93.40999755859376,
          "verticalOscillation": 7.5,
          "elevationGain": 0.0,
          "elevationLoss": 0.0
        },
        {
          "km": 6,
          "distancia_m": 100.0,
          "duracion_seg": 30.3,
          "ritmo_min_km": "5:02",
          "averageHR": 114.0,
          "maxHR": 117.0,
          "averageRunCadence": 160.1875,
          "averagePower": 287.0,
          "groundContactTime": 250.0,
          "strideLength": 102.60999755859376,
          "verticalOscillation": 7.840000152587891,
          "elevationGain": 1.0,
          "elevationLoss": 0.0
        },
        {
          "km": 7,
          "distancia_m": 100.0,
          "duracion_seg": 38.4,
          "ritmo_min_km": "6:24",
          "averageHR": 120.0,
          "maxHR": 123.0,
          "averageRunCadence": 176.1875,
          "averagePower": 309.0,
          "groundContactTime": 257.8999938964844,
          "strideLength": 104.0,
          "verticalOscillation": 8.40999984741211,
          "elevationGain": 0.0,
          "elevationLoss": 0.0
        },
        {
          "km": 8,
          "distancia_m": 100.0,
          "duracion_seg": 22.5,
          "ritmo_min_km": "3:45",
          "averageHR": 131.0,
          "maxHR": 143.0,
          "averageRunCadence": 190.484375,
          "averagePower": 411.0,
          "groundContactTime": 209.8000030517578,
          "strideLength": 132.7800048828125,
          "verticalOscillation": 7.70999984741211,
          "elevationGain": 0.0,
          "elevationLoss": 0.0
        },
        {
          "km": 9,
          "distancia_m": 100.0,
          "duracion_seg": 42.4,
          "ritmo_min_km": "7:03",
          "averageHR": 141.0,
          "maxHR": 148.0,
          "averageRunCadence": 172.78125,
          "averagePower": 267.0,
          "groundContactTime": 272.79998779296875,
          "strideLength": 90.2,
          "verticalOscillation": 8.0,
          "elevationGain": 0.0,
          "elevationLoss": 0.0
        },
        {
          "km": 10,
          "distancia_m": 100.0,
          "duracion_seg": 25.1,
          "ritmo_min_km": "4:10",
          "averageHR": 139.0,
          "maxHR": 149.0,
          "averageRunCadence": 198.4375,
          "averagePower": 376.0,
          "groundContactTime": 217.8000030517578,
          "strideLength": 112.0300048828125,
          "verticalOscillation": 7.3599998474121096,
          "elevationGain": 0.0,
          "elevationLoss": 1.0
        },
        {
          "km": 11,
          "distancia_m": 100.0,
          "duracion_seg": 41.7,
          "ritmo_min_km": "6:56",
          "averageHR": 144.0,
          "maxHR": 152.0,
          "averageRunCadence": 173.3125,
          "averagePower": 240.0,
          "groundContactTime": 278.3999938964844,
          "strideLength": 81.32000122070313,
          "verticalOscillation": 7.640000152587891,
          "elevationGain": 0.0,
          "elevationLoss": 0.0
        },
        {
          "km": 12,
          "distancia_m": 100.0,
          "duracion_seg": 25.8,
          "ritmo_min_km": "4:18",
          "averageHR": 131.0,
          "maxHR": 134.0,
          "averageRunCadence": 188.234375,
          "averagePower": 332.0,
          "groundContactTime": 232.8000030517578,
          "strideLength": 105.94000244140625,
          "verticalOscillation": 7.3500000000000005,
          "elevationGain": 0.0,
          "elevationLoss": 0.0
        },
        {
          "km": 13,
          "distancia_m": 100.0,
          "duracion_seg": 43.5,
          "ritmo_min_km": "7:14",
          "averageHR": 118.0,
          "maxHR": 128.0,
          "averageRunCadence": 167.515625,
          "averagePower": 254.0,
          "groundContactTime": 274.6000061035156,
          "strideLength": 88.14000244140625,
          "verticalOscillation": 7.75,
          "elevationGain": 0.0,
          "elevationLoss": 0.0
        },
        {
          "km": 14,
          "distancia_m": 200.0,
          "duracion_seg": 76.3,
          "ritmo_min_km": "6:21",
          "averageHR": 124.0,
          "maxHR": 127.0,
          "averageRunCadence": 166.515625,
          "averagePower": 265.0,
          "groundContactTime": 271.1000061035156,
          "strideLength": 91.92999877929688,
          "verticalOscillation": 8.11999969482422,
          "elevationGain": 0.0,
          "elevationLoss": 0.0
        },
        {
          "km": 15,
          "distancia_m": 400.0,
          "duracion_seg": 88.3,
          "ritmo_min_km": "3:40",
          "averageHR": 145.0,
          "maxHR": 162.0,
          "averageRunCadence": 195.265625,
          "averagePower": 448.0,
          "groundContactTime": 201.3000030517578,
          "strideLength": 139.94000244140625,
          "verticalOscillation": 8.35999984741211,
          "elevationGain": 0.0,
          "elevationLoss": 0.0
        },
        {
          "km": 16,
          "distancia_m": 200.0,
          "duracion_seg": 79.1,
          "ritmo_min_km": "6:35",
          "averageHR": 147.0,
          "maxHR": 163.0,
          "averageRunCadence": 170.5,
          "averagePower": 247.0,
          "groundContactTime": 281.8999938964844,
          "strideLength": 82.57000122070313,
          "verticalOscillation": 7.769999694824219,
          "elevationGain": 0.0,
          "elevationLoss": 0.0
        },
        {
          "km": 17,
          "distancia_m": 400.0,
          "duracion_seg": 88.7,
          "ritmo_min_km": "3:41",
          "averageHR": 153.0,
          "maxHR": 158.0,
          "averageRunCadence": 197.15625,
          "averagePower": 453.0,
          "groundContactTime": 202.39999389648438,
          "strideLength": 133.7300048828125,
          "verticalOscillation": 8.069999694824219,
          "elevationGain": 0.0,
          "elevationLoss": 0.0
        },
        {
          "km": 18,
          "distancia_m": 200.0,
          "duracion_seg": 85.4,
          "ritmo_min_km": "7:06",
          "averageHR": 149.0,
          "maxHR": 158.0,
          "averageRunCadence": 159.984375,
          "averagePower": 238.0,
          "groundContactTime": 291.79998779296875,
          "strideLength": 87.37999877929688,
          "verticalOscillation": 7.909999847412109,
          "elevationGain": 0.0,
          "elevationLoss": 0.0
        },
        {
          "km": 19,
          "distancia_m": 400.0,
          "duracion_seg": 87.4,
          "ritmo_min_km": "3:38",
          "averageHR": 152.0,
          "maxHR": 164.0,
          "averageRunCadence": 195.5625,
          "averagePower": 455.0,
          "groundContactTime": 197.60000610351562,
          "strideLength": 142.19000244140625,
          "verticalOscillation": 8.35999984741211,
          "elevationGain": 0.0,
          "elevationLoss": 0.0
        },
        {
          "km": 20,
          "distancia_m": 200.0,
          "duracion_seg": 88.3,
          "ritmo_min_km": "7:21",
          "averageHR": 146.0,
          "maxHR": 164.0,
          "averageRunCadence": 161.5,
          "averagePower": 230.0,
          "groundContactTime": 287.29998779296875,
          "strideLength": 82.82000122070313,
          "verticalOscillation": 7.880000305175781,
          "elevationGain": 0.0,
          "elevationLoss": 0.0
        },
        {
          "km": 21,
          "distancia_m": 400.0,
          "duracion_seg": 91.1,
          "ritmo_min_km": "3:47",
          "averageHR": 154.0,
          "maxHR": 161.0,
          "averageRunCadence": 194.515625,
          "averagePower": 458.0,
          "groundContactTime": 203.39999389648438,
          "strideLength": 137.20000000000002,
          "verticalOscillation": 8.319999694824219,
          "elevationGain": 1.0,
          "elevationLoss": 0.0
        },
        {
          "km": 22,
          "distancia_m": 200.0,
          "duracion_seg": 113.9,
          "ritmo_min_km": "9:29",
          "averageHR": 136.0,
          "maxHR": 160.0,
          "averageRunCadence": 127.140625,
          "averagePower": 153.0,
          "groundContactTime": 296.20001220703125,
          "strideLength": 78.47000122070312,
          "verticalOscillation": 6.580000305175782,
          "elevationGain": 0.0,
          "elevationLoss": 1.0
        },
        {
          "km": 23,
          "distancia_m": 400.0,
          "duracion_seg": 87.4,
          "ritmo_min_km": "3:38",
          "averageHR": 149.0,
          "maxHR": 159.0,
          "averageRunCadence": 193.34375,
          "averagePower": 459.0,
          "groundContactTime": 198.89999389648438,
          "strideLength": 144.0,
          "verticalOscillation": 8.55,
          "elevationGain": 0.0,
          "elevationLoss": 0.0
        },
        {
          "km": 24,
          "distancia_m": 200.0,
          "duracion_seg": 97.9,
          "ritmo_min_km": "8:09",
          "averageHR": 145.0,
          "maxHR": 159.0,
          "averageRunCadence": 141.21875,
          "averagePower": 186.0,
          "groundContactTime": 286.5,
          "strideLength": 77.05999755859375,
          "verticalOscillation": 7.219999694824219,
          "elevationGain": 0.0,
          "elevationLoss": 0.0
        },
        {
          "km": 25,
          "distancia_m": 400.0,
          "duracion_seg": 88.4,
          "ritmo_min_km": "3:40",
          "averageHR": 154.0,
          "maxHR": 164.0,
          "averageRunCadence": 192.703125,
          "averagePower": 452.0,
          "groundContactTime": 207.1999969482422,
          "strideLength": 135.84000244140626,
          "verticalOscillation": 8.36999969482422,
          "elevationGain": 0.0,
          "elevationLoss": 0.0
        },
        {
          "km": 26,
          "distancia_m": 200.0,
          "duracion_seg": 111.1,
          "ritmo_min_km": "9:15",
          "averageHR": 143.0,
          "maxHR": 164.0,
          "averageRunCadence": 138.953125,
          "averagePower": 175.0,
          "groundContactTime": 288.79998779296875,
          "strideLength": 79.07999877929689,
          "verticalOscillation": 6.919999694824219,
          "elevationGain": 0.0,
          "elevationLoss": 0.0
        },
        {
          "km": 27,
          "distancia_m": 400.0,
          "duracion_seg": 83.8,
          "ritmo_min_km": "3:29",
          "averageHR": 153.0,
          "maxHR": 163.0,
          "averageRunCadence": 192.40625,
          "averagePower": 454.0,
          "groundContactTime": 190.8000030517578,
          "strideLength": 147.7800048828125,
          "verticalOscillation": 8.36999969482422,
          "elevationGain": 0.0,
          "elevationLoss": 0.0
        },
        {
          "km": 28,
          "distancia_m": 200.0,
          "duracion_seg": 109.8,
          "ritmo_min_km": "9:09",
          "averageHR": 146.0,
          "maxHR": 164.0,
          "averageRunCadence": 137.59375,
          "averagePower": 170.0,
          "groundContactTime": 286.5,
          "strideLength": 77.30000000000001,
          "verticalOscillation": 6.690000152587891,
          "elevationGain": 0.0,
          "elevationLoss": 1.0
        },
        {
          "km": 29,
          "distancia_m": 400.0,
          "duracion_seg": 95.0,
          "ritmo_min_km": "3:57",
          "averageHR": 157.0,
          "maxHR": 165.0,
          "averageRunCadence": 188.765625,
          "averagePower": 447.0,
          "groundContactTime": 210.39999389648438,
          "strideLength": 138.79000244140624,
          "verticalOscillation": 8.65999984741211,
          "elevationGain": 1.0,
          "elevationLoss": 0.0
        },
        {
          "km": 30,
          "distancia_m": 200.0,
          "duracion_seg": 148.8,
          "ritmo_min_km": "12:23",
          "averageHR": 131.0,
          "maxHR": 161.0,
          "averageRunCadence": 102.109375,
          "averagePower": 93.0,
          "groundContactTime": 288.0,
          "strideLength": 71.55999755859375,
          "verticalOscillation": 5.820000076293946,
          "elevationGain": 0.0,
          "elevationLoss": 1.0
        },
        {
          "km": 31,
          "distancia_m": 1000.0,
          "duracion_seg": 401.1,
          "ritmo_min_km": "6:41",
          "averageHR": 133.0,
          "maxHR": 165.0,
          "averageRunCadence": 133.671875,
          "averagePower": 221.0,
          "groundContactTime": 243.1999969482422,
          "strideLength": 106.5199951171875,
          "verticalOscillation": 7.15,
          "elevationGain": 0.0,
          "elevationLoss": 0.0
        },
        {
          "km": 32,
          "distancia_m": 1000.0,
          "duracion_seg": 360.8,
          "ritmo_min_km": "6:00",
          "averageHR": 142.0,
          "maxHR": 164.0,
          "averageRunCadence": 157.53125,
          "averagePower": 272.0,
          "groundContactTime": 257.3999938964844,
          "strideLength": 101.07000122070313,
          "verticalOscillation": 8.080000305175782,
          "elevationGain": 0.0,
          "elevationLoss": 0.0
        },
        {
          "km": 33,
          "distancia_m": 1000.0,
          "duracion_seg": 387.1,
          "ritmo_min_km": "6:27",
          "averageHR": 139.0,
          "maxHR": 149.0,
          "averageRunCadence": 171.8125,
          "averagePower": 281.0,
          "groundContactTime": 268.0,
          "strideLength": 93.85000000000001,
          "verticalOscillation": 8.080000305175782,
          "elevationGain": 6.0,
          "elevationLoss": 13.0
        },
        {
          "km": 34,
          "distancia_m": 627.41,
          "duracion_seg": 242.6,
          "ritmo_min_km": "6:26",
          "averageHR": 135.0,
          "maxHR": 137.0,
          "averageRunCadence": 174.34375,
          "averagePower": 268.0,
          "groundContactTime": 270.29998779296875,
          "strideLength": 89.87000122070313,
          "verticalOscillation": 7.95999984741211,
          "elevationGain": 0.0,
          "elevationLoss": 0.0
        },
        {
          "km": 35,
          "duracion_seg": 0.4,
          "averageHR": 133.0,
          "maxHR": 133.0,
          "averageRunCadence": 174.0,
          "averagePower": 0.0,
          "groundContactTime": 276.0,
          "strideLength": 83.0,
          "verticalOscillation": 7.690000152587891,
          "elevationGain": 0.0,
          "elevationLoss": 0.0
        }
      ]
    },
    {
      "activityId": 22190761601,
      "activityName": "Remo indoor",
      "startTimeLocal": "2026-03-16 06:44:00",
      "activityType": "indoor_rowing",
      "distance": 0.0,
      "duration": 303.0920104980469,
      "elapsedDuration": 303.0920104980469,
      "averageSpeed": 0.0,
      "calories": 35.0,
      "averageHR": 94.0,
      "maxHR": 129.0,
      "aerobicTrainingEffect": 0.20000000298023224,
      "anaerobicTrainingEffect": 0.20000000298023224,
      "trainingEffectLabel": "UNKNOWN",
      "activityTrainingLoad": 6.720184326171875,
      "moderateIntensityMinutes": 2,
      "vigorousIntensityMinutes": 1,
      "differenceBodyBattery": -1,
      "lapCount": 1,
      "duracion_min": 5.1
    },
    {
      "activityId": 22190705917,
      "activityName": "Ciclismo en sala",
      "startTimeLocal": "2026-03-16 06:22:35",
      "activityType": "indoor_cycling",
      "distance": 0.0,
      "duration": 1205.779052734375,
      "elapsedDuration": 1205.779052734375,
      "averageSpeed": 0.0,
      "calories": 63.0,
      "averageHR": 70.0,
      "maxHR": 98.0,
      "aerobicTrainingEffect": 0.10000000149011612,
      "anaerobicTrainingEffect": 0.0,
      "trainingEffectLabel": "UNKNOWN",
      "activityTrainingLoad": 1.684722900390625,
      "moderateIntensityMinutes": 3,
      "vigorousIntensityMinutes": 0,
      "differenceBodyBattery": -2,
      "lapCount": 1,
      "duracion_min": 20.1
    },
    {
      "activityId": 22182355923,
      "activityName": "Tarifa Carrera",
      "startTimeLocal": "2026-03-15 07:54:56",
      "activityType": "running",
      "distance": 425.79998779296875,
      "duration": 167.39300537109375,
      "elapsedDuration": 167.39300537109375,
      "averageSpeed": 2.5439999103546143,
      "maxSpeed": 2.9579999446868896,
      "calories": 34.0,
      "averageHR": 136.0,
      "maxHR": 144.0,
      "averageRunningCadenceInStepsPerMinute": 171.453125,
      "avgStrideLength": 89.10000000000001,
      "avgVerticalOscillation": 7.8699996948242195,
      "elevationGain": 1.0,
      "elevationLoss": 0.0,
      "aerobicTrainingEffect": 1.7999999523162842,
      "anaerobicTrainingEffect": 0.0,
      "trainingEffectLabel": "RECOVERY",
      "activityTrainingLoad": 24.16326904296875,
      "moderateIntensityMinutes": 0,
      "vigorousIntensityMinutes": 2,
      "differenceBodyBattery": -1,
      "locationName": "Tarifa",
      "lapCount": 1,
      "steps": 478,
      "avgPower": 265.0,
      "maxPower": 338.0,
      "normPower": 272.0,
      "ritmo_min_km": "6:33",
      "duracion_min": 2.8,
      "distancia_km": 0.43,
      "splits": [
        {
          "km": 1,
          "distancia_m": 425.8,
          "duracion_seg": 167.4,
          "ritmo_min_km": "6:33",
          "averageHR": 136.0,
          "maxHR": 144.0,
          "averageRunCadence": 171.453125,
          "averagePower": 265.0,
          "groundContactTime": 271.6000061035156,
          "strideLength": 89.10000000000001,
          "verticalOscillation": 7.8699996948242195,
          "elevationGain": 1.0,
          "elevationLoss": 0.0
        }
      ]
    }
  ]
}